{
  "template": "roguelike",
  "gameFiles": [
    "data.js",
    "game.js",
    "render.js",
    "main.js"
  ],
  "slug": "engine-test",
  "title": "Engine Test",
  "currentVersion": 13,
  "versions": [
    {
      "version": 1,
      "date": "2026-02-12",
      "issue": null,
      "description": "Initial release"
    },
    {
      "version": 2,
      "date": "2026-02-12",
      "issue": null,
      "description": "Published v2"
    },
    {
      "version": 3,
      "date": "2026-02-15",
      "issue": null,
      "description": "Published v3"
    },
    {
      "version": 4,
      "date": "2026-02-15",
      "issue": null,
      "description": "Published v4"
    },
    {
      "version": 5,
      "date": "2026-02-15",
      "issue": null,
      "description": "Published v5"
    },
    {
      "version": 6,
      "date": "2026-02-15",
      "issue": null,
      "description": "Published v6"
    },
    {
      "version": 7,
      "date": "2026-02-15",
      "issue": null,
      "description": "Published v7"
    },
    {
      "version": 8,
      "date": "2026-02-15",
      "issue": null,
      "description": "Published v8"
    },
    {
      "version": 9,
      "date": "2026-02-15",
      "issue": null,
      "description": "Published v9"
    },
    {
      "version": 10,
      "date": "2026-02-15",
      "issue": null,
      "description": "Published v10"
    },
    {
      "version": 11,
      "date": "2026-02-15",
      "issue": null,
      "description": "Published v11"
    },
    {
      "version": 12,
      "date": "2026-02-15",
      "issue": null,
      "description": "Published v12"
    },
    {
      "version": 13,
      "date": "2026-02-15",
      "issue": null,
      "description": "Published v13"
    }
  ],
  "sdkVersion": 1,
  "engineVersion": 1
}
